[
  {
    "city": "Toronto",
    "lat": 43.666667,
    "lng": -79.416667,
    "country": "Canada",
    "iso2": "CA",
    "admin": "Ontario",
    "capital": "admin",
    "population": 5213000,
    "population_proper": 3934421
  },
  {
    "city": "Montréal",
    "lat": 45.5,
    "lng": -73.583333,
    "country": "Canada",
    "iso2": "CA",
    "admin": "Québec",
    "capital": "",
    "population": 3678000,
    "population_proper": 2356556
  },
  {
    "city": "Vancouver",
    "lat": 49.25,
    "lng": -123.133333,
    "country": "Canada",
    "iso2": "CA",
    "admin": "British Columbia",
    "capital": "",
    "population": 2313328,
    "population_proper": 603502
  },
  {
    "city": "Ottawa",
    "lat": 45.416667,
    "lng": -75.7,
    "country": "Canada",
    "iso2": "CA",
    "admin": "Ontario",
    "capital": "primary",
    "population": 1145000,
    "population_proper": 812129
  },
  {
    "city": "Calgary",
    "lat": 51.083333,
    "lng": -114.083333,
    "country": "Canada",
    "iso2": "CA",
    "admin": "Alberta",
    "capital": "",
    "population": 1110000,
    "population_proper": 915322
  },
  {
    "city": "Edmonton",
    "lat": 53.55,
    "lng": -113.5,
    "country": "Canada",
    "iso2": "CA",
    "admin": "Alberta",
    "capital": "admin",
    "population": 1058000,
    "population_proper": 712391
  },
  {
    "city": "Hamilton",
    "lat": 43.256101,
    "lng": -79.857484,
    "country": "Canada",
    "iso2": "CA",
    "admin": "Ontario",
    "capital": "",
    "population": 721053,
    "population_proper": 519949
  },
  {
    "city": "Winnipeg",
    "lat": 49.883333,
    "lng": -97.166667,
    "country": "Canada",
    "iso2": "CA",
    "admin": "Manitoba",
    "capital": "admin",
    "population": 632063,
    "population_proper": 575313
  },
  {
    "city": "Québec",
    "lat": 46.8,
    "lng": -71.25,
    "country": "Canada",
    "iso2": "CA",
    "admin": "Québec",
    "capital": "admin",
    "population": 624177,
    "population_proper": 528595
  },
  {
    "city": "Oshawa",
    "lat": 43.9,
    "lng": -78.866667,
    "country": "Canada",
    "iso2": "CA",
    "admin": "Ontario",
    "capital": "",
    "population": 450963,
    "population_proper": 247989
  },
  {
    "city": "Kitchener",
    "lat": 43.446976,
    "lng": -80.472484,
    "country": "Canada",
    "iso2": "CA",
    "admin": "Ontario",
    "capital": "",
    "population": 417001,
    "population_proper": 409112
  },
  {
    "city": "Halifax",
    "lat": 44.65,
    "lng": -63.6,
    "country": "Canada",
    "iso2": "CA",
    "admin": "Nova Scotia",
    "capital": "admin",
    "population": 359111,
    "population_proper": 222874
  },
  {
    "city": "London",
    "lat": 42.983333,
    "lng": -81.25,
    "country": "Canada",
    "iso2": "CA",
    "admin": "Ontario",
    "capital": "",
    "population": 346765,
    "population_proper": 335035
  },
  {
    "city": "Windsor",
    "lat": 42.301649,
    "lng": -83.030744,
    "country": "Canada",
    "iso2": "CA",
    "admin": "Ontario",
    "capital": "",
    "population": 319246,
    "population_proper": 210891
  },
  {
    "city": "Victoria",
    "lat": 48.450234,
    "lng": -123.343529,
    "country": "Canada",
    "iso2": "CA",
    "admin": "British Columbia",
    "capital": "admin",
    "population": 289625,
    "population_proper": 251358
  },
  {
    "city": "Saskatoon",
    "lat": 52.133333,
    "lng": -106.666667,
    "country": "Canada",
    "iso2": "CA",
    "admin": "Saskatchewan",
    "capital": "",
    "population": 198958,
    "population_proper": 189193
  },
  {
    "city": "Barrie",
    "lat": 44.383333,
    "lng": -79.7,
    "country": "Canada",
    "iso2": "CA",
    "admin": "Ontario",
    "capital": "",
    "population": 182041,
    "population_proper": 119732
  },
  {
    "city": "Regina",
    "lat": 50.45,
    "lng": -104.616667,
    "country": "Canada",
    "iso2": "CA",
    "admin": "Saskatchewan",
    "capital": "admin",
    "population": 176183,
    "population_proper": 176183
  },
  {
    "city": "Sudbury",
    "lat": 46.5,
    "lng": -80.966667,
    "country": "Canada",
    "iso2": "CA",
    "admin": "Ontario",
    "capital": "",
    "population": 157857,
    "population_proper": 80507
  },
  {
    "city": "Abbotsford",
    "lat": 49.05,
    "lng": -122.3,
    "country": "Canada",
    "iso2": "CA",
    "admin": "British Columbia",
    "capital": "",
    "population": 151683,
    "population_proper": 151683
  },
  {
    "city": "Sarnia",
    "lat": 42.978417,
    "lng": -82.388177,
    "country": "Canada",
    "iso2": "CA",
    "admin": "Ontario",
    "capital": "",
    "population": 144172,
    "population_proper": 82998
  },
  {
    "city": "Sherbrooke",
    "lat": 45.4,
    "lng": -71.9,
    "country": "Canada",
    "iso2": "CA",
    "admin": "Québec",
    "capital": "",
    "population": 139652,
    "population_proper": 129447
  },
  {
    "city": "Saint John’s",
    "lat": 47.55,
    "lng": -52.666667,
    "country": "Canada",
    "iso2": "CA",
    "admin": "Newfoundland and Labrador",
    "capital": "admin",
    "population": 131469,
    "population_proper": 99182
  },
  {
    "city": "Kelowna",
    "lat": 49.9,
    "lng": -119.483333,
    "country": "Canada",
    "iso2": "CA",
    "admin": "British Columbia",
    "capital": "",
    "population": 125109,
    "population_proper": 95306
  },
  {
    "city": "Trois-Rivières",
    "lat": 46.35,
    "lng": -72.55,
    "country": "Canada",
    "iso2": "CA",
    "admin": "Québec",
    "capital": "",
    "population": 119693,
    "population_proper": 116409
  },
  {
    "city": "Kingston",
    "lat": 44.3,
    "lng": -76.566667,
    "country": "Canada",
    "iso2": "CA",
    "admin": "Ontario",
    "capital": "",
    "population": 114195,
    "population_proper": 102400
  },
  {
    "city": "Thunder Bay",
    "lat": 48.4,
    "lng": -89.233333,
    "country": "Canada",
    "iso2": "CA",
    "admin": "Ontario",
    "capital": "",
    "population": 99334,
    "population_proper": 97374
  },
  {
    "city": "Moncton",
    "lat": 46.09652,
    "lng": -64.79757,
    "country": "Canada",
    "iso2": "CA",
    "admin": "New Brunswick",
    "capital": "",
    "population": 90635,
    "population_proper": 87467
  },
  {
    "city": "Saint John",
    "lat": 45.230798,
    "lng": -66.095316,
    "country": "Canada",
    "iso2": "CA",
    "admin": "New Brunswick",
    "capital": "",
    "population": 87857,
    "population_proper": 54449
  },
  {
    "city": "Nanaimo",
    "lat": 49.15,
    "lng": -123.916667,
    "country": "Canada",
    "iso2": "CA",
    "admin": "British Columbia",
    "capital": "",
    "population": 84905,
    "population_proper": 80491
  },
  {
    "city": "Peterborough",
    "lat": 44.3,
    "lng": -78.333333,
    "country": "Canada",
    "iso2": "CA",
    "admin": "Ontario",
    "capital": "",
    "population": 83627,
    "population_proper": 75877
  },
  {
    "city": "Saint-Jérôme",
    "lat": 45.766667,
    "lng": -74,
    "country": "Canada",
    "iso2": "CA",
    "admin": "Québec",
    "capital": "",
    "population": 78439,
    "population_proper": 54948
  },
  {
    "city": "Red Deer",
    "lat": 52.266667,
    "lng": -113.8,
    "country": "Canada",
    "iso2": "CA",
    "admin": "Alberta",
    "capital": "",
    "population": 74857,
    "population_proper": 73593
  },
  {
    "city": "Lethbridge",
    "lat": 49.7,
    "lng": -112.833333,
    "country": "Canada",
    "iso2": "CA",
    "admin": "Alberta",
    "capital": "",
    "population": 70617,
    "population_proper": 58571
  },
  {
    "city": "Kamloops",
    "lat": 50.666667,
    "lng": -120.333333,
    "country": "Canada",
    "iso2": "CA",
    "admin": "British Columbia",
    "capital": "",
    "population": 68714,
    "population_proper": 68628
  },
  {
    "city": "Prince George",
    "lat": 53.916667,
    "lng": -122.766667,
    "country": "Canada",
    "iso2": "CA",
    "admin": "British Columbia",
    "capital": "",
    "population": 65558,
    "population_proper": 62707
  },
  {
    "city": "Medicine Hat",
    "lat": 50.033333,
    "lng": -110.683333,
    "country": "Canada",
    "iso2": "CA",
    "admin": "Alberta",
    "capital": "",
    "population": 63138,
    "population_proper": 53626
  },
  {
    "city": "Drummondville",
    "lat": 45.883333,
    "lng": -72.483333,
    "country": "Canada",
    "iso2": "CA",
    "admin": "Québec",
    "capital": "",
    "population": 59489,
    "population_proper": 54123
  },
  {
    "city": "Chicoutimi",
    "lat": 48.45,
    "lng": -71.066667,
    "country": "Canada",
    "iso2": "CA",
    "admin": "Québec",
    "capital": "",
    "population": 53940,
    "population_proper": 53940
  },
  {
    "city": "Fredericton",
    "lat": 45.910648,
    "lng": -66.658649,
    "country": "Canada",
    "iso2": "CA",
    "admin": "New Brunswick",
    "capital": "admin",
    "population": 52337,
    "population_proper": 36713
  },
  {
    "city": "Chilliwack",
    "lat": 49.166667,
    "lng": -121.95,
    "country": "Canada",
    "iso2": "CA",
    "admin": "British Columbia",
    "capital": "",
    "population": 51942,
    "population_proper": 51942
  },
  {
    "city": "North Bay",
    "lat": 46.3,
    "lng": -79.45,
    "country": "Canada",
    "iso2": "CA",
    "admin": "Ontario",
    "capital": "",
    "population": 50170,
    "population_proper": 41807
  },
  {
    "city": "Shawinigan-Sud",
    "lat": 46.528557,
    "lng": -72.751453,
    "country": "Canada",
    "iso2": "CA",
    "admin": "Québec",
    "capital": "",
    "population": 49161,
    "population_proper": 34342
  },
  {
    "city": "Cornwall",
    "lat": 45.016667,
    "lng": -74.733333,
    "country": "Canada",
    "iso2": "CA",
    "admin": "Ontario",
    "capital": "",
    "population": 48821,
    "population_proper": 46382
  },
  {
    "city": "Joliette",
    "lat": 46.034,
    "lng": -73.441,
    "country": "Canada",
    "iso2": "CA",
    "admin": "Québec",
    "capital": "",
    "population": 45361,
    "population_proper": 34772
  },
  {
    "city": "Belleville",
    "lat": 44.166667,
    "lng": -77.383333,
    "country": "Canada",
    "iso2": "CA",
    "admin": "Ontario",
    "capital": "",
    "population": 43990,
    "population_proper": 43990
  },
  {
    "city": "Charlottetown",
    "lat": 46.238225,
    "lng": -63.139481,
    "country": "Canada",
    "iso2": "CA",
    "admin": "Prince Edward Island",
    "capital": "admin",
    "population": 42402,
    "population_proper": 31293
  },
  {
    "city": "Victoriaville",
    "lat": 46.063106,
    "lng": -71.958802,
    "country": "Canada",
    "iso2": "CA",
    "admin": "Québec",
    "capital": "",
    "population": 41500,
    "population_proper": 34426
  },
  {
    "city": "Grande Prairie",
    "lat": 55.166667,
    "lng": -118.8,
    "country": "Canada",
    "iso2": "CA",
    "admin": "Alberta",
    "capital": "",
    "population": 41462,
    "population_proper": 40845
  },
  {
    "city": "Penticton",
    "lat": 49.5,
    "lng": -119.583333,
    "country": "Canada",
    "iso2": "CA",
    "admin": "British Columbia",
    "capital": "",
    "population": 37721,
    "population_proper": 30349
  },
  {
    "city": "Sydney",
    "lat": 46.15,
    "lng": -60.166667,
    "country": "Canada",
    "iso2": "CA",
    "admin": "Nova Scotia",
    "capital": "",
    "population": 37538,
    "population_proper": 37538
  },
  {
    "city": "Orillia",
    "lat": 44.6,
    "lng": -79.416667,
    "country": "Canada",
    "iso2": "CA",
    "admin": "Ontario",
    "capital": "",
    "population": 37483,
    "population_proper": 30178
  },
  {
    "city": "Rimouski",
    "lat": 48.433333,
    "lng": -68.516667,
    "country": "Canada",
    "iso2": "CA",
    "admin": "Québec",
    "capital": "",
    "population": 35584,
    "population_proper": 35584
  },
  {
    "city": "Timmins",
    "lat": 48.466667,
    "lng": -81.333333,
    "country": "Canada",
    "iso2": "CA",
    "admin": "Ontario",
    "capital": "",
    "population": 34974,
    "population_proper": 32901
  },
  {
    "city": "Prince Albert",
    "lat": 53.2,
    "lng": -105.75,
    "country": "Canada",
    "iso2": "CA",
    "admin": "Saskatchewan",
    "capital": "",
    "population": 34609,
    "population_proper": 24678
  },
  {
    "city": "Campbell River",
    "lat": 50.016667,
    "lng": -125.25,
    "country": "Canada",
    "iso2": "CA",
    "admin": "British Columbia",
    "capital": "",
    "population": 33430,
    "population_proper": 26453
  },
  {
    "city": "Courtenay",
    "lat": 49.683333,
    "lng": -125,
    "country": "Canada",
    "iso2": "CA",
    "admin": "British Columbia",
    "capital": "",
    "population": 32793,
    "population_proper": 25099
  },
  {
    "city": "Orangeville",
    "lat": 43.916366,
    "lng": -80.096671,
    "country": "Canada",
    "iso2": "CA",
    "admin": "Ontario",
    "capital": "",
    "population": 32640,
    "population_proper": 28984
  },
  {
    "city": "Moose Jaw",
    "lat": 50.4,
    "lng": -105.55,
    "country": "Canada",
    "iso2": "CA",
    "admin": "Saskatchewan",
    "capital": "",
    "population": 32166,
    "population_proper": 30707
  },
  {
    "city": "Brandon",
    "lat": 49.833333,
    "lng": -99.95,
    "country": "Canada",
    "iso2": "CA",
    "admin": "Manitoba",
    "capital": "",
    "population": 28418,
    "population_proper": 26234
  },
  {
    "city": "Brockville",
    "lat": 44.594958,
    "lng": -75.682133,
    "country": "Canada",
    "iso2": "CA",
    "admin": "Ontario",
    "capital": "",
    "population": 26458,
    "population_proper": 23886
  },
  {
    "city": "Saint-Georges",
    "lat": 46.116667,
    "lng": -70.683333,
    "country": "Canada",
    "iso2": "CA",
    "admin": "Québec",
    "capital": "",
    "population": 26149,
    "population_proper": 26149
  },
  {
    "city": "Sept-Îles",
    "lat": 50.2,
    "lng": -66.383333,
    "country": "Canada",
    "iso2": "CA",
    "admin": "Québec",
    "capital": "",
    "population": 25686,
    "population_proper": 25686
  },
  {
    "city": "Rouyn-Noranda",
    "lat": 48.25,
    "lng": -79.016667,
    "country": "Canada",
    "iso2": "CA",
    "admin": "Québec",
    "capital": "",
    "population": 24602,
    "population_proper": 24023
  },
  {
    "city": "Whitehorse",
    "lat": 60.716667,
    "lng": -135.05,
    "country": "Canada",
    "iso2": "CA",
    "admin": "Yukon",
    "capital": "admin",
    "population": 23276,
    "population_proper": 23272
  },
  {
    "city": "Owen Sound",
    "lat": 44.566667,
    "lng": -80.85,
    "country": "Canada",
    "iso2": "CA",
    "admin": "Ontario",
    "capital": "",
    "population": 22625,
    "population_proper": 22625
  },
  {
    "city": "Fort McMurray",
    "lat": 56.733333,
    "lng": -111.383333,
    "country": "Canada",
    "iso2": "CA",
    "admin": "Alberta",
    "capital": "",
    "population": 21863,
    "population_proper": 21863
  },
  {
    "city": "Corner Brook",
    "lat": 48.95,
    "lng": -57.933333,
    "country": "Canada",
    "iso2": "CA",
    "admin": "Newfoundland and Labrador",
    "capital": "",
    "population": 20791,
    "population_proper": 18693
  },
  {
    "city": "Val-d’Or",
    "lat": 48.116667,
    "lng": -77.766667,
    "country": "Canada",
    "iso2": "CA",
    "admin": "Québec",
    "capital": "",
    "population": 20625,
    "population_proper": 20625
  },
  {
    "city": "New Glasgow",
    "lat": 45.583333,
    "lng": -62.633333,
    "country": "Canada",
    "iso2": "CA",
    "admin": "Nova Scotia",
    "capital": "",
    "population": 20322,
    "population_proper": 19445
  },
  {
    "city": "Terrace",
    "lat": 54.5,
    "lng": -128.583333,
    "country": "Canada",
    "iso2": "CA",
    "admin": "British Columbia",
    "capital": "",
    "population": 19443,
    "population_proper": 10101
  },
  {
    "city": "North Battleford",
    "lat": 52.766667,
    "lng": -108.283333,
    "country": "Canada",
    "iso2": "CA",
    "admin": "Saskatchewan",
    "capital": "",
    "population": 19440,
    "population_proper": 12003
  },
  {
    "city": "Yellowknife",
    "lat": 62.45,
    "lng": -114.35,
    "country": "Canada",
    "iso2": "CA",
    "admin": "Northwest Territories",
    "capital": "admin",
    "population": 19234,
    "population_proper": 18083
  },
  {
    "city": "Fort Saint John",
    "lat": 56.25,
    "lng": -120.833333,
    "country": "Canada",
    "iso2": "CA",
    "admin": "British Columbia",
    "capital": "",
    "population": 18776,
    "population_proper": 17402
  },
  {
    "city": "Cranbrook",
    "lat": 49.516667,
    "lng": -115.766667,
    "country": "Canada",
    "iso2": "CA",
    "admin": "British Columbia",
    "capital": "",
    "population": 18610,
    "population_proper": 17370
  },
  {
    "city": "Edmundston",
    "lat": 47.36226,
    "lng": -68.327874,
    "country": "Canada",
    "iso2": "CA",
    "admin": "New Brunswick",
    "capital": "",
    "population": 17894,
    "population_proper": 17894
  },
  {
    "city": "Rivière-du-Loup",
    "lat": 47.833333,
    "lng": -69.533333,
    "country": "Canada",
    "iso2": "CA",
    "admin": "Québec",
    "capital": "",
    "population": 16403,
    "population_proper": 16403
  },
  {
    "city": "Camrose",
    "lat": 53.016667,
    "lng": -112.816667,
    "country": "Canada",
    "iso2": "CA",
    "admin": "Alberta",
    "capital": "",
    "population": 15808,
    "population_proper": 15686
  },
  {
    "city": "Pembroke",
    "lat": 45.816667,
    "lng": -77.116667,
    "country": "Canada",
    "iso2": "CA",
    "admin": "Ontario",
    "capital": "",
    "population": 15551,
    "population_proper": 15551
  },
  {
    "city": "Yorkton",
    "lat": 51.216667,
    "lng": -102.466667,
    "country": "Canada",
    "iso2": "CA",
    "admin": "Saskatchewan",
    "capital": "",
    "population": 15172,
    "population_proper": 13583
  },
  {
    "city": "Swift Current",
    "lat": 50.283333,
    "lng": -107.766667,
    "country": "Canada",
    "iso2": "CA",
    "admin": "Saskatchewan",
    "capital": "",
    "population": 14906,
    "population_proper": 14703
  },
  {
    "city": "Prince Rupert",
    "lat": 54.316667,
    "lng": -130.333333,
    "country": "Canada",
    "iso2": "CA",
    "admin": "British Columbia",
    "capital": "",
    "population": 14708,
    "population_proper": 14708
  },
  {
    "city": "Williams Lake",
    "lat": 52.116667,
    "lng": -122.15,
    "country": "Canada",
    "iso2": "CA",
    "admin": "British Columbia",
    "capital": "",
    "population": 14168,
    "population_proper": 10554
  },
  {
    "city": "Brooks",
    "lat": 50.566667,
    "lng": -111.9,
    "country": "Canada",
    "iso2": "CA",
    "admin": "Alberta",
    "capital": "",
    "population": 14163,
    "population_proper": 12744
  },
  {
    "city": "Quesnel",
    "lat": 52.983333,
    "lng": -122.483333,
    "country": "Canada",
    "iso2": "CA",
    "admin": "British Columbia",
    "capital": "",
    "population": 13788,
    "population_proper": 13788
  },
  {
    "city": "Thompson",
    "lat": 55.75,
    "lng": -97.866667,
    "country": "Canada",
    "iso2": "CA",
    "admin": "Manitoba",
    "capital": "",
    "population": 13727,
    "population_proper": 12467
  },
  {
    "city": "Dolbeau",
    "lat": 48.866667,
    "lng": -72.233333,
    "country": "Canada",
    "iso2": "CA",
    "admin": "Québec",
    "capital": "",
    "population": 13337,
    "population_proper": 12916
  },
  {
    "city": "Powell River",
    "lat": 49.883333,
    "lng": -124.55,
    "country": "Canada",
    "iso2": "CA",
    "admin": "British Columbia",
    "capital": "",
    "population": 12779,
    "population_proper": 3220
  },
  {
    "city": "Wetaskiwin",
    "lat": 52.966667,
    "lng": -113.383333,
    "country": "Canada",
    "iso2": "CA",
    "admin": "Alberta",
    "capital": "",
    "population": 11823,
    "population_proper": 11302
  },
  {
    "city": "Nelson",
    "lat": 49.483333,
    "lng": -117.283333,
    "country": "Canada",
    "iso2": "CA",
    "admin": "British Columbia",
    "capital": "",
    "population": 11779,
    "population_proper": 9813
  },
  {
    "city": "Mont-Laurier",
    "lat": 46.55,
    "lng": -75.5,
    "country": "Canada",
    "iso2": "CA",
    "admin": "Québec",
    "capital": "",
    "population": 11642,
    "population_proper": 11642
  },
  {
    "city": "Kenora",
    "lat": 49.766667,
    "lng": -94.466667,
    "country": "Canada",
    "iso2": "CA",
    "admin": "Ontario",
    "capital": "",
    "population": 10852,
    "population_proper": 10852
  },
  {
    "city": "Dawson Creek",
    "lat": 55.766667,
    "lng": -120.233333,
    "country": "Canada",
    "iso2": "CA",
    "admin": "British Columbia",
    "capital": "",
    "population": 10802,
    "population_proper": 10551
  },
  {
    "city": "Amos",
    "lat": 48.566667,
    "lng": -78.116667,
    "country": "Canada",
    "iso2": "CA",
    "admin": "Québec",
    "capital": "",
    "population": 10516,
    "population_proper": 10435
  },
  {
    "city": "Baie-Comeau",
    "lat": 49.216667,
    "lng": -68.15,
    "country": "Canada",
    "iso2": "CA",
    "admin": "Québec",
    "capital": "",
    "population": 10435,
    "population_proper": 7181
  },
  {
    "city": "Hinton",
    "lat": 53.4,
    "lng": -117.583333,
    "country": "Canada",
    "iso2": "CA",
    "admin": "Alberta",
    "capital": "",
    "population": 10265,
    "population_proper": 9889
  },
  {
    "city": "Selkirk",
    "lat": 50.15,
    "lng": -96.883333,
    "country": "Canada",
    "iso2": "CA",
    "admin": "Manitoba",
    "capital": "",
    "population": 9986,
    "population_proper": 9653
  },
  {
    "city": "Steinbach",
    "lat": 49.516667,
    "lng": -96.683333,
    "country": "Canada",
    "iso2": "CA",
    "admin": "Manitoba",
    "capital": "",
    "population": 9729,
    "population_proper": 9607
  },
  {
    "city": "Weyburn",
    "lat": 49.666667,
    "lng": -103.85,
    "country": "Canada",
    "iso2": "CA",
    "admin": "Saskatchewan",
    "capital": "",
    "population": 9362,
    "population_proper": 9243
  },
  {
    "city": "Amherst",
    "lat": 45.830019,
    "lng": -64.210024,
    "country": "Canada",
    "iso2": "CA",
    "admin": "Nova Scotia",
    "capital": "",
    "population": 9336,
    "population_proper": 7927
  },
  {
    "city": "Kapuskasing",
    "lat": 49.416667,
    "lng": -82.433333,
    "country": "Canada",
    "iso2": "CA",
    "admin": "Ontario",
    "capital": "",
    "population": 9240,
    "population_proper": 8224
  },
  {
    "city": "Dauphin",
    "lat": 51.15,
    "lng": -100.05,
    "country": "Canada",
    "iso2": "CA",
    "admin": "Manitoba",
    "capital": "",
    "population": 9077,
    "population_proper": 8418
  },
  {
    "city": "Dryden",
    "lat": 49.783333,
    "lng": -92.833333,
    "country": "Canada",
    "iso2": "CA",
    "admin": "Ontario",
    "capital": "",
    "population": 7862,
    "population_proper": 7862
  },
  {
    "city": "Revelstoke",
    "lat": 51,
    "lng": -118.183333,
    "country": "Canada",
    "iso2": "CA",
    "admin": "British Columbia",
    "capital": "",
    "population": 7668,
    "population_proper": 7533
  },
  {
    "city": "Happy Valley",
    "lat": 53.3,
    "lng": -60.3,
    "country": "Canada",
    "iso2": "CA",
    "admin": "Newfoundland and Labrador",
    "capital": "",
    "population": 7572,
    "population_proper": 1047
  },
  {
    "city": "Banff",
    "lat": 51.166667,
    "lng": -115.566667,
    "country": "Canada",
    "iso2": "CA",
    "admin": "Alberta",
    "capital": "",
    "population": 7502,
    "population_proper": 6292
  },
  {
    "city": "Yarmouth",
    "lat": 43.833965,
    "lng": -66.113926,
    "country": "Canada",
    "iso2": "CA",
    "admin": "Nova Scotia",
    "capital": "",
    "population": 7500,
    "population_proper": 7366
  },
  {
    "city": "La Sarre",
    "lat": 48.8,
    "lng": -79.2,
    "country": "Canada",
    "iso2": "CA",
    "admin": "Québec",
    "capital": "",
    "population": 7206,
    "population_proper": 5527
  },
  {
    "city": "Parry Sound",
    "lat": 45.333333,
    "lng": -80.033333,
    "country": "Canada",
    "iso2": "CA",
    "admin": "Ontario",
    "capital": "",
    "population": 7105,
    "population_proper": 6469
  },
  {
    "city": "Stephenville",
    "lat": 48.55,
    "lng": -58.566667,
    "country": "Canada",
    "iso2": "CA",
    "admin": "Newfoundland and Labrador",
    "capital": "",
    "population": 7054,
    "population_proper": 6278
  },
  {
    "city": "Antigonish",
    "lat": 45.616667,
    "lng": -61.966667,
    "country": "Canada",
    "iso2": "CA",
    "admin": "Nova Scotia",
    "capital": "",
    "population": 6739,
    "population_proper": 5003
  },
  {
    "city": "Flin Flon",
    "lat": 54.766667,
    "lng": -101.883333,
    "country": "Canada",
    "iso2": "CA",
    "admin": "Manitoba",
    "capital": "",
    "population": 6393,
    "population_proper": 6002
  },
  {
    "city": "Fort Nelson",
    "lat": 58.816667,
    "lng": -122.533333,
    "country": "Canada",
    "iso2": "CA",
    "admin": "British Columbia",
    "capital": "",
    "population": 6315,
    "population_proper": 6315
  },
  {
    "city": "Smithers",
    "lat": 54.766667,
    "lng": -127.166667,
    "country": "Canada",
    "iso2": "CA",
    "admin": "British Columbia",
    "capital": "",
    "population": 6245,
    "population_proper": 5438
  },
  {
    "city": "Iqaluit",
    "lat": 63.733333,
    "lng": -68.5,
    "country": "Canada",
    "iso2": "CA",
    "admin": "Nunavut",
    "capital": "admin",
    "population": 6124,
    "population_proper": 6124
  },
  {
    "city": "Bathurst",
    "lat": 47.558376,
    "lng": -65.656517,
    "country": "Canada",
    "iso2": "CA",
    "admin": "New Brunswick",
    "capital": "",
    "population": 6111,
    "population_proper": 4496
  },
  {
    "city": "The Pas",
    "lat": 53.816667,
    "lng": -101.233333,
    "country": "Canada",
    "iso2": "CA",
    "admin": "Manitoba",
    "capital": "",
    "population": 6055,
    "population_proper": 3802
  },
  {
    "city": "Norway House",
    "lat": 53.966667,
    "lng": -97.833333,
    "country": "Canada",
    "iso2": "CA",
    "admin": "Manitoba",
    "capital": "",
    "population": 6000,
    "population_proper": 5000
  },
  {
    "city": "Meadow Lake",
    "lat": 54.129722,
    "lng": -108.434722,
    "country": "Canada",
    "iso2": "CA",
    "admin": "Saskatchewan",
    "capital": "",
    "population": 5882,
    "population_proper": 4281
  },
  {
    "city": "Vegreville",
    "lat": 53.5,
    "lng": -112.05,
    "country": "Canada",
    "iso2": "CA",
    "admin": "Alberta",
    "capital": "",
    "population": 5813,
    "population_proper": 5678
  },
  {
    "city": "Stettler",
    "lat": 52.333333,
    "lng": -112.683333,
    "country": "Canada",
    "iso2": "CA",
    "admin": "Alberta",
    "capital": "",
    "population": 5494,
    "population_proper": 5405
  },
  {
    "city": "Peace River",
    "lat": 56.233333,
    "lng": -117.283333,
    "country": "Canada",
    "iso2": "CA",
    "admin": "Alberta",
    "capital": "",
    "population": 5340,
    "population_proper": 4689
  },
  {
    "city": "New Liskeard",
    "lat": 47.5,
    "lng": -79.666667,
    "country": "Canada",
    "iso2": "CA",
    "admin": "Ontario",
    "capital": "",
    "population": 5203,
    "population_proper": 5203
  },
  {
    "city": "Hearst",
    "lat": 49.7,
    "lng": -83.666667,
    "country": "Canada",
    "iso2": "CA",
    "admin": "Ontario",
    "capital": "",
    "population": 5043,
    "population_proper": 4746
  },
  {
    "city": "Creston",
    "lat": 49.1,
    "lng": -116.516667,
    "country": "Canada",
    "iso2": "CA",
    "admin": "British Columbia",
    "capital": "",
    "population": 4816,
    "population_proper": 4816
  },
  {
    "city": "Marathon",
    "lat": 48.75,
    "lng": -86.366667,
    "country": "Canada",
    "iso2": "CA",
    "admin": "Ontario",
    "capital": "",
    "population": 4627,
    "population_proper": 4627
  },
  {
    "city": "Cochrane",
    "lat": 49.066667,
    "lng": -81.016667,
    "country": "Canada",
    "iso2": "CA",
    "admin": "Ontario",
    "capital": "",
    "population": 4441,
    "population_proper": 4441
  },
  {
    "city": "Kindersley",
    "lat": 51.466667,
    "lng": -109.133333,
    "country": "Canada",
    "iso2": "CA",
    "admin": "Saskatchewan",
    "capital": "",
    "population": 4383,
    "population_proper": 4249
  },
  {
    "city": "Liverpool",
    "lat": 44.038414,
    "lng": -64.718433,
    "country": "Canada",
    "iso2": "CA",
    "admin": "Nova Scotia",
    "capital": "",
    "population": 4331,
    "population_proper": 4331
  },
  {
    "city": "Melville",
    "lat": 50.933333,
    "lng": -102.8,
    "country": "Canada",
    "iso2": "CA",
    "admin": "Saskatchewan",
    "capital": "",
    "population": 4279,
    "population_proper": 4173
  },
  {
    "city": "Channel-Port aux Basques",
    "lat": 47.566667,
    "lng": -59.15,
    "country": "Canada",
    "iso2": "CA",
    "admin": "Newfoundland and Labrador",
    "capital": "",
    "population": 4220,
    "population_proper": 2244
  },
  {
    "city": "Deer Lake",
    "lat": 49.183333,
    "lng": -57.433333,
    "country": "Canada",
    "iso2": "CA",
    "admin": "Newfoundland and Labrador",
    "capital": "",
    "population": 4163,
    "population_proper": 3743
  },
  {
    "city": "Saint-Augustin",
    "lat": 51.233333,
    "lng": -58.65,
    "country": "Canada",
    "iso2": "CA",
    "admin": "Québec",
    "capital": "",
    "population": 3961,
    "population_proper": 3961
  },
  {
    "city": "Digby",
    "lat": 44.578466,
    "lng": -65.783525,
    "country": "Canada",
    "iso2": "CA",
    "admin": "Nova Scotia",
    "capital": "",
    "population": 3949,
    "population_proper": 2052
  },
  {
    "city": "Jasper",
    "lat": 52.883333,
    "lng": -118.083333,
    "country": "Canada",
    "iso2": "CA",
    "admin": "Alberta",
    "capital": "",
    "population": 3907,
    "population_proper": 3102
  },
  {
    "city": "Hay River",
    "lat": 60.85,
    "lng": -115.7,
    "country": "Canada",
    "iso2": "CA",
    "admin": "Northwest Territories",
    "capital": "",
    "population": 3900,
    "population_proper": 3648
  },
  {
    "city": "Windsor",
    "lat": 44.958995,
    "lng": -64.144786,
    "country": "Canada",
    "iso2": "CA",
    "admin": "Nova Scotia",
    "capital": "",
    "population": 3864,
    "population_proper": 3654
  },
  {
    "city": "La Ronge",
    "lat": 55.1,
    "lng": -105.3,
    "country": "Canada",
    "iso2": "CA",
    "admin": "Saskatchewan",
    "capital": "",
    "population": 3783,
    "population_proper": 3071
  },
  {
    "city": "Deer Lake",
    "lat": 52.616667,
    "lng": -94.066667,
    "country": "Canada",
    "iso2": "CA",
    "admin": "Ontario",
    "capital": "",
    "population": 3743,
    "population_proper": 3743
  },
  {
    "city": "Gaspé",
    "lat": 48.833333,
    "lng": -64.483333,
    "country": "Canada",
    "iso2": "CA",
    "admin": "Québec",
    "capital": "",
    "population": 3677,
    "population_proper": 3331
  },
  {
    "city": "Atikokan",
    "lat": 48.75,
    "lng": -91.616667,
    "country": "Canada",
    "iso2": "CA",
    "admin": "Ontario",
    "capital": "",
    "population": 3625,
    "population_proper": 3625
  },
  {
    "city": "Gander",
    "lat": 48.95,
    "lng": -54.55,
    "country": "Canada",
    "iso2": "CA",
    "admin": "Newfoundland and Labrador",
    "capital": "",
    "population": 3345,
    "population_proper": 3345
  },
  {
    "city": "Fort Chipewyan",
    "lat": 58.716667,
    "lng": -111.15,
    "country": "Canada",
    "iso2": "CA",
    "admin": "Alberta",
    "capital": "",
    "population": 3222,
    "population_proper": 3222
  },
  {
    "city": "Shelburne",
    "lat": 43.753356,
    "lng": -65.246074,
    "country": "Canada",
    "iso2": "CA",
    "admin": "Nova Scotia",
    "capital": "",
    "population": 3167,
    "population_proper": 1939
  },
  {
    "city": "Inuvik",
    "lat": 68.35,
    "lng": -133.7,
    "country": "Canada",
    "iso2": "CA",
    "admin": "Northwest Territories",
    "capital": "",
    "population": 3022,
    "population_proper": 3022
  },
  {
    "city": "Lac La Biche",
    "lat": 54.771944,
    "lng": -111.964722,
    "country": "Canada",
    "iso2": "CA",
    "admin": "Alberta",
    "capital": "",
    "population": 2986,
    "population_proper": 2919
  },
  {
    "city": "Lillooet",
    "lat": 50.683333,
    "lng": -121.933333,
    "country": "Canada",
    "iso2": "CA",
    "admin": "British Columbia",
    "capital": "",
    "population": 2893,
    "population_proper": 2893
  },
  {
    "city": "Chapleau",
    "lat": 47.833333,
    "lng": -83.4,
    "country": "Canada",
    "iso2": "CA",
    "admin": "Ontario",
    "capital": "",
    "population": 2663,
    "population_proper": 2663
  },
  {
    "city": "Burns Lake",
    "lat": 54.216667,
    "lng": -125.766667,
    "country": "Canada",
    "iso2": "CA",
    "admin": "British Columbia",
    "capital": "",
    "population": 2635,
    "population_proper": 2631
  },
  {
    "city": "Gimli",
    "lat": 50.633333,
    "lng": -97,
    "country": "Canada",
    "iso2": "CA",
    "admin": "Manitoba",
    "capital": "",
    "population": 2623,
    "population_proper": 2009
  },
  {
    "city": "Athabasca",
    "lat": 54.716667,
    "lng": -113.266667,
    "country": "Canada",
    "iso2": "CA",
    "admin": "Alberta",
    "capital": "",
    "population": 2539,
    "population_proper": 2260
  },
  {
    "city": "Nelson House",
    "lat": 55.8,
    "lng": -98.85,
    "country": "Canada",
    "iso2": "CA",
    "admin": "Manitoba",
    "capital": "",
    "population": 2500,
    "population_proper": 2500
  },
  {
    "city": "Rankin Inlet",
    "lat": 62.816667,
    "lng": -92.083333,
    "country": "Canada",
    "iso2": "CA",
    "admin": "Nunavut",
    "capital": "",
    "population": 2472,
    "population_proper": 2334
  },
  {
    "city": "Port Hardy",
    "lat": 50.716667,
    "lng": -127.5,
    "country": "Canada",
    "iso2": "CA",
    "admin": "British Columbia",
    "capital": "",
    "population": 2295,
    "population_proper": 2295
  },
  {
    "city": "Biggar",
    "lat": 52.05,
    "lng": -107.983333,
    "country": "Canada",
    "iso2": "CA",
    "admin": "Saskatchewan",
    "capital": "",
    "population": 2192,
    "population_proper": 2068
  },
  {
    "city": "Wiarton",
    "lat": 44.733333,
    "lng": -81.133333,
    "country": "Canada",
    "iso2": "CA",
    "admin": "Ontario",
    "capital": "",
    "population": 2182,
    "population_proper": 2182
  },
  {
    "city": "Wawa",
    "lat": 47.99473,
    "lng": -84.77002,
    "country": "Canada",
    "iso2": "CA",
    "admin": "Ontario",
    "capital": "",
    "population": 2174,
    "population_proper": 2174
  },
  {
    "city": "Hudson Bay",
    "lat": 52.85,
    "lng": -102.383333,
    "country": "Canada",
    "iso2": "CA",
    "admin": "Saskatchewan",
    "capital": "",
    "population": 2157,
    "population_proper": 1661
  },
  {
    "city": "Matagami",
    "lat": 49.75,
    "lng": -77.633333,
    "country": "Canada",
    "iso2": "CA",
    "admin": "Québec",
    "capital": "",
    "population": 1966,
    "population_proper": 1183
  },
  {
    "city": "Arviat",
    "lat": 61.116667,
    "lng": -94.05,
    "country": "Canada",
    "iso2": "CA",
    "admin": "Nunavut",
    "capital": "",
    "population": 1868,
    "population_proper": 1868
  },
  {
    "city": "Attawapiskat",
    "lat": 52.916667,
    "lng": -82.433333,
    "country": "Canada",
    "iso2": "CA",
    "admin": "Ontario",
    "capital": "",
    "population": 1802,
    "population_proper": 1802
  },
  {
    "city": "Red Lake",
    "lat": 51.033333,
    "lng": -93.833333,
    "country": "Canada",
    "iso2": "CA",
    "admin": "Ontario",
    "capital": "",
    "population": 1765,
    "population_proper": 1765
  },
  {
    "city": "Moosonee",
    "lat": 51.266667,
    "lng": -80.65,
    "country": "Canada",
    "iso2": "CA",
    "admin": "Ontario",
    "capital": "",
    "population": 1725,
    "population_proper": 1725
  },
  {
    "city": "Tofino",
    "lat": 49.133333,
    "lng": -125.9,
    "country": "Canada",
    "iso2": "CA",
    "admin": "British Columbia",
    "capital": "",
    "population": 1655,
    "population_proper": 1655
  },
  {
    "city": "Igloolik",
    "lat": 69.4,
    "lng": -81.8,
    "country": "Canada",
    "iso2": "CA",
    "admin": "Nunavut",
    "capital": "",
    "population": 1612,
    "population_proper": 1612
  },
  {
    "city": "Inukjuak",
    "lat": 58.45334,
    "lng": -78.102493,
    "country": "Canada",
    "iso2": "CA",
    "admin": "Québec",
    "capital": "",
    "population": 1597,
    "population_proper": 1597
  },
  {
    "city": "Little Current",
    "lat": 45.966667,
    "lng": -81.933333,
    "country": "Canada",
    "iso2": "CA",
    "admin": "Ontario",
    "capital": "",
    "population": 1595,
    "population_proper": 1595
  },
  {
    "city": "Baker Lake",
    "lat": 64.316667,
    "lng": -96.016667,
    "country": "Canada",
    "iso2": "CA",
    "admin": "Nunavut",
    "capital": "",
    "population": 1584,
    "population_proper": 1584
  },
  {
    "city": "Pond Inlet",
    "lat": 72.7,
    "lng": -78,
    "country": "Canada",
    "iso2": "CA",
    "admin": "Nunavut",
    "capital": "",
    "population": 1549,
    "population_proper": 1549
  },
  {
    "city": "Cap-Chat",
    "lat": 49.083333,
    "lng": -66.683333,
    "country": "Canada",
    "iso2": "CA",
    "admin": "Québec",
    "capital": "",
    "population": 1484,
    "population_proper": 1466
  },
  {
    "city": "Cambridge Bay",
    "lat": 69.116667,
    "lng": -105.033333,
    "country": "Canada",
    "iso2": "CA",
    "admin": "Nunavut",
    "capital": "",
    "population": 1477,
    "population_proper": 1477
  },
  {
    "city": "Thessalon",
    "lat": 46.25,
    "lng": -83.55,
    "country": "Canada",
    "iso2": "CA",
    "admin": "Ontario",
    "capital": "",
    "population": 1464,
    "population_proper": 1369
  },
  {
    "city": "New Bella Bella",
    "lat": 52.166667,
    "lng": -128.133333,
    "country": "Canada",
    "iso2": "CA",
    "admin": "British Columbia",
    "capital": "",
    "population": 1400,
    "population_proper": 1400
  },
  {
    "city": "Cobalt",
    "lat": 47.383333,
    "lng": -79.683333,
    "country": "Canada",
    "iso2": "CA",
    "admin": "Ontario",
    "capital": "",
    "population": 1372,
    "population_proper": 1372
  },
  {
    "city": "Cape Dorset",
    "lat": 64.233333,
    "lng": -76.55,
    "country": "Canada",
    "iso2": "CA",
    "admin": "Nunavut",
    "capital": "",
    "population": 1326,
    "population_proper": 1326
  },
  {
    "city": "Pangnirtung",
    "lat": 66.133333,
    "lng": -65.75,
    "country": "Canada",
    "iso2": "CA",
    "admin": "Nunavut",
    "capital": "",
    "population": 1320,
    "population_proper": 1320
  },
  {
    "city": "West Dawson",
    "lat": 64.066667,
    "lng": -139.45,
    "country": "Canada",
    "iso2": "CA",
    "admin": "Yukon",
    "capital": "",
    "population": 1319,
    "population_proper": 1319
  },
  {
    "city": "Kugluktuk",
    "lat": 67.833333,
    "lng": -115.083333,
    "country": "Canada",
    "iso2": "CA",
    "admin": "Nunavut",
    "capital": "",
    "population": 1302,
    "population_proper": 1302
  },
  {
    "city": "Geraldton",
    "lat": 49.716667,
    "lng": -86.966667,
    "country": "Canada",
    "iso2": "CA",
    "admin": "Ontario",
    "capital": "",
    "population": 1290,
    "population_proper": 1290
  },
  {
    "city": "Gillam",
    "lat": 56.35,
    "lng": -94.7,
    "country": "Canada",
    "iso2": "CA",
    "admin": "Manitoba",
    "capital": "",
    "population": 1281,
    "population_proper": 1281
  },
  {
    "city": "Kuujjuaq",
    "lat": 58.1,
    "lng": -68.4,
    "country": "Canada",
    "iso2": "CA",
    "admin": "Québec",
    "capital": "",
    "population": 1273,
    "population_proper": 1273
  },
  {
    "city": "Lake Louise",
    "lat": 51.433333,
    "lng": -116.183333,
    "country": "Canada",
    "iso2": "CA",
    "admin": "Alberta",
    "capital": "",
    "population": 1248,
    "population_proper": 1248
  },
  {
    "city": "Nipigon",
    "lat": 49.016667,
    "lng": -88.25,
    "country": "Canada",
    "iso2": "CA",
    "admin": "Ontario",
    "capital": "",
    "population": 1204,
    "population_proper": 1204
  },
  {
    "city": "Nain",
    "lat": 56.55,
    "lng": -61.683333,
    "country": "Canada",
    "iso2": "CA",
    "admin": "Newfoundland and Labrador",
    "capital": "",
    "population": 1151,
    "population_proper": 1151
  },
  {
    "city": "Gjoa Haven",
    "lat": 68.633333,
    "lng": -95.916667,
    "country": "Canada",
    "iso2": "CA",
    "admin": "Nunavut",
    "capital": "",
    "population": 1109,
    "population_proper": 1109
  },
  {
    "city": "Fort McPherson",
    "lat": 67.433333,
    "lng": -134.866667,
    "country": "Canada",
    "iso2": "CA",
    "admin": "Northwest Territories",
    "capital": "",
    "population": 1069,
    "population_proper": 1069
  },
  {
    "city": "Argentia",
    "lat": 47.3,
    "lng": -54,
    "country": "Canada",
    "iso2": "CA",
    "admin": "Newfoundland and Labrador",
    "capital": "",
    "population": 1063,
    "population_proper": 1063
  },
  {
    "city": "Norman Wells",
    "lat": 65.283333,
    "lng": -126.85,
    "country": "Canada",
    "iso2": "CA",
    "admin": "Northwest Territories",
    "capital": "",
    "population": 1027,
    "population_proper": 273
  },
  {
    "city": "Churchill",
    "lat": 58.766667,
    "lng": -94.166667,
    "country": "Canada",
    "iso2": "CA",
    "admin": "Manitoba",
    "capital": "",
    "population": 1000,
    "population_proper": 923
  },
  {
    "city": "Repulse Bay",
    "lat": 66.516667,
    "lng": -86.233333,
    "country": "Canada",
    "iso2": "CA",
    "admin": "Nunavut",
    "capital": "",
    "population": 1000,
    "population_proper": 748
  },
  {
    "city": "Tuktoyaktuk",
    "lat": 69.45,
    "lng": -133.066667,
    "country": "Canada",
    "iso2": "CA",
    "admin": "Northwest Territories",
    "capital": "",
    "population": 929,
    "population_proper": 870
  },
  {
    "city": "Berens River",
    "lat": 52.366667,
    "lng": -97.033333,
    "country": "Canada",
    "iso2": "CA",
    "admin": "Manitoba",
    "capital": "",
    "population": 892,
    "population_proper": 153
  },
  {
    "city": "Shamattawa",
    "lat": 55.85,
    "lng": -92.083333,
    "country": "Canada",
    "iso2": "CA",
    "admin": "Manitoba",
    "capital": "",
    "population": 870,
    "population_proper": 870
  },
  {
    "city": "Baddeck",
    "lat": 46.1,
    "lng": -60.75,
    "country": "Canada",
    "iso2": "CA",
    "admin": "Nova Scotia",
    "capital": "",
    "population": 852,
    "population_proper": 852
  },
  {
    "city": "Coral Harbour",
    "lat": 64.133333,
    "lng": -83.166667,
    "country": "Canada",
    "iso2": "CA",
    "admin": "Nunavut",
    "capital": "",
    "population": 834,
    "population_proper": 834
  },
  {
    "city": "La Scie",
    "lat": 49.966667,
    "lng": -55.583333,
    "country": "Canada",
    "iso2": "CA",
    "admin": "Newfoundland and Labrador",
    "capital": "",
    "population": 817,
    "population_proper": 817
  },
  {
    "city": "Watson Lake",
    "lat": 60.116667,
    "lng": -128.8,
    "country": "Canada",
    "iso2": "CA",
    "admin": "Yukon",
    "capital": "",
    "population": 802,
    "population_proper": 802
  },
  {
    "city": "Taloyoak",
    "lat": 69.533333,
    "lng": -93.533333,
    "country": "Canada",
    "iso2": "CA",
    "admin": "Nunavut",
    "capital": "",
    "population": 774,
    "population_proper": 774
  },
  {
    "city": "Natashquan",
    "lat": 50.183333,
    "lng": -61.816667,
    "country": "Canada",
    "iso2": "CA",
    "admin": "Québec",
    "capital": "",
    "population": 722,
    "population_proper": 722
  },
  {
    "city": "Buchans",
    "lat": 48.816667,
    "lng": -56.866667,
    "country": "Canada",
    "iso2": "CA",
    "admin": "Newfoundland and Labrador",
    "capital": "",
    "population": 685,
    "population_proper": 685
  },
  {
    "city": "Hall Beach",
    "lat": 68.766667,
    "lng": -81.2,
    "country": "Canada",
    "iso2": "CA",
    "admin": "Nunavut",
    "capital": "",
    "population": 654,
    "population_proper": 654
  },
  {
    "city": "Arctic Bay",
    "lat": 73.033333,
    "lng": -85.166667,
    "country": "Canada",
    "iso2": "CA",
    "admin": "Nunavut",
    "capital": "",
    "population": 604,
    "population_proper": 604
  },
  {
    "city": "Fort Good Hope",
    "lat": 66.266667,
    "lng": -128.633333,
    "country": "Canada",
    "iso2": "CA",
    "admin": "Northwest Territories",
    "capital": "",
    "population": 597,
    "population_proper": 597
  },
  {
    "city": "Mingan",
    "lat": 50.3,
    "lng": -64.016667,
    "country": "Canada",
    "iso2": "CA",
    "admin": "Québec",
    "capital": "",
    "population": 588,
    "population_proper": 588
  },
  {
    "city": "Kangirsuk",
    "lat": 60.016667,
    "lng": -70.033333,
    "country": "Canada",
    "iso2": "CA",
    "admin": "Québec",
    "capital": "",
    "population": 549,
    "population_proper": 549
  },
  {
    "city": "Sandspit",
    "lat": 53.239111,
    "lng": -131.818769,
    "country": "Canada",
    "iso2": "CA",
    "admin": "British Columbia",
    "capital": "",
    "population": 538,
    "population_proper": 538
  },
  {
    "city": "Délįne",
    "lat": 65.183333,
    "lng": -123.416667,
    "country": "Canada",
    "iso2": "CA",
    "admin": "Northwest Territories",
    "capital": "",
    "population": 525,
    "population_proper": 262
  },
  {
    "city": "Fort Smith",
    "lat": 60,
    "lng": -111.883333,
    "country": "Canada",
    "iso2": "CA",
    "admin": "Northwest Territories",
    "capital": "",
    "population": 518,
    "population_proper": 518
  },
  {
    "city": "Cartwright",
    "lat": 53.7,
    "lng": -57.016667,
    "country": "Canada",
    "iso2": "CA",
    "admin": "Newfoundland and Labrador",
    "capital": "",
    "population": 505,
    "population_proper": 505
  },
  {
    "city": "Holman",
    "lat": 70.733333,
    "lng": -117.75,
    "country": "Canada",
    "iso2": "CA",
    "admin": "Northwest Territories",
    "capital": "",
    "population": 500,
    "population_proper": 398
  },
  {
    "city": "Lynn Lake",
    "lat": 56.85,
    "lng": -101.05,
    "country": "Canada",
    "iso2": "CA",
    "admin": "Manitoba",
    "capital": "",
    "population": 482,
    "population_proper": 482
  },
  {
    "city": "Schefferville",
    "lat": 54.8,
    "lng": -66.816667,
    "country": "Canada",
    "iso2": "CA",
    "admin": "Québec",
    "capital": "",
    "population": 471,
    "population_proper": 471
  },
  {
    "city": "Trout River",
    "lat": 49.483333,
    "lng": -58.116667,
    "country": "Canada",
    "iso2": "CA",
    "admin": "Newfoundland and Labrador",
    "capital": "",
    "population": 452,
    "population_proper": 452
  },
  {
    "city": "Forteau Bay",
    "lat": 51.45,
    "lng": -56.95,
    "country": "Canada",
    "iso2": "CA",
    "admin": "Newfoundland and Labrador",
    "capital": "",
    "population": 448,
    "population_proper": 448
  },
  {
    "city": "Fort Resolution",
    "lat": 61.166667,
    "lng": -113.683333,
    "country": "Canada",
    "iso2": "CA",
    "admin": "Northwest Territories",
    "capital": "",
    "population": 448,
    "population_proper": 448
  },
  {
    "city": "Hopedale",
    "lat": 55.45,
    "lng": -60.216667,
    "country": "Canada",
    "iso2": "CA",
    "admin": "Newfoundland and Labrador",
    "capital": "",
    "population": 442,
    "population_proper": 442
  },
  {
    "city": "Pukatawagan",
    "lat": 55.733333,
    "lng": -101.316667,
    "country": "Canada",
    "iso2": "CA",
    "admin": "Manitoba",
    "capital": "",
    "population": 431,
    "population_proper": 431
  },
  {
    "city": "Trepassey",
    "lat": 46.733333,
    "lng": -53.366667,
    "country": "Canada",
    "iso2": "CA",
    "admin": "Newfoundland and Labrador",
    "capital": "",
    "population": 398,
    "population_proper": 398
  },
  {
    "city": "Kimmirut",
    "lat": 62.85,
    "lng": -69.883333,
    "country": "Canada",
    "iso2": "CA",
    "admin": "Nunavut",
    "capital": "",
    "population": 385,
    "population_proper": 385
  },
  {
    "city": "Chesterfield Inlet",
    "lat": 63.333333,
    "lng": -90.7,
    "country": "Canada",
    "iso2": "CA",
    "admin": "Nunavut",
    "capital": "",
    "population": 374,
    "population_proper": 374
  },
  {
    "city": "Eastmain",
    "lat": 52.233333,
    "lng": -78.516667,
    "country": "Canada",
    "iso2": "CA",
    "admin": "Québec",
    "capital": "",
    "population": 335,
    "population_proper": 335
  },
  {
    "city": "Dease Lake",
    "lat": 58.476697,
    "lng": -129.96146,
    "country": "Canada",
    "iso2": "CA",
    "admin": "British Columbia",
    "capital": "",
    "population": 303,
    "population_proper": 303
  },
  {
    "city": "Paulatuk",
    "lat": 69.383333,
    "lng": -123.983333,
    "country": "Canada",
    "iso2": "CA",
    "admin": "Northwest Territories",
    "capital": "",
    "population": 294,
    "population_proper": 294
  },
  {
    "city": "Fort Simpson",
    "lat": 61.85,
    "lng": -121.333333,
    "country": "Canada",
    "iso2": "CA",
    "admin": "Northwest Territories",
    "capital": "",
    "population": 283,
    "population_proper": 283
  },
  {
    "city": "Brochet",
    "lat": 57.883333,
    "lng": -101.666667,
    "country": "Canada",
    "iso2": "CA",
    "admin": "Manitoba",
    "capital": "",
    "population": 278,
    "population_proper": 278
  },
  {
    "city": "Cat Lake",
    "lat": 51.716667,
    "lng": -91.8,
    "country": "Canada",
    "iso2": "CA",
    "admin": "Ontario",
    "capital": "",
    "population": 277,
    "population_proper": 277
  },
  {
    "city": "Radisson",
    "lat": 53.783333,
    "lng": -77.616667,
    "country": "Canada",
    "iso2": "CA",
    "admin": "Québec",
    "capital": "",
    "population": 270,
    "population_proper": 270
  },
  {
    "city": "Port-Menier",
    "lat": 49.816667,
    "lng": -64.35,
    "country": "Canada",
    "iso2": "CA",
    "admin": "Québec",
    "capital": "",
    "population": 263,
    "population_proper": 263
  },
  {
    "city": "Resolute",
    "lat": 74.683333,
    "lng": -94.9,
    "country": "Canada",
    "iso2": "CA",
    "admin": "Nunavut",
    "capital": "",
    "population": 250,
    "population_proper": 229
  },
  {
    "city": "Saint Anthony",
    "lat": 51.383333,
    "lng": -55.6,
    "country": "Canada",
    "iso2": "CA",
    "admin": "Newfoundland and Labrador",
    "capital": "",
    "population": 224,
    "population_proper": 224
  },
  {
    "city": "Port Hope Simpson",
    "lat": 52.533333,
    "lng": -56.3,
    "country": "Canada",
    "iso2": "CA",
    "admin": "Newfoundland and Labrador",
    "capital": "",
    "population": 197,
    "population_proper": 197
  },
  {
    "city": "Oxford House",
    "lat": 54.95,
    "lng": -95.266667,
    "country": "Canada",
    "iso2": "CA",
    "admin": "Manitoba",
    "capital": "",
    "population": 184,
    "population_proper": 184
  },
  {
    "city": "Tsiigehtchic",
    "lat": 67.433333,
    "lng": -133.75,
    "country": "Canada",
    "iso2": "CA",
    "admin": "Northwest Territories",
    "capital": "",
    "population": 175,
    "population_proper": 175
  },
  {
    "city": "Ivujivik",
    "lat": 62.416667,
    "lng": -77.9,
    "country": "Canada",
    "iso2": "CA",
    "admin": "Québec",
    "capital": "",
    "population": 156,
    "population_proper": 156
  },
  {
    "city": "Stony Rapids",
    "lat": 59.266667,
    "lng": -105.833333,
    "country": "Canada",
    "iso2": "CA",
    "admin": "Saskatchewan",
    "capital": "",
    "population": 152,
    "population_proper": 152
  },
  {
    "city": "Alert",
    "lat": 82.483333,
    "lng": -62.25,
    "country": "Canada",
    "iso2": "CA",
    "admin": "Nunavut",
    "capital": "",
    "population": 125,
    "population_proper": 70
  },
  {
    "city": "Fort Severn",
    "lat": 55.983333,
    "lng": -87.65,
    "country": "Canada",
    "iso2": "CA",
    "admin": "Ontario",
    "capital": "",
    "population": 125,
    "population_proper": 125
  },
  {
    "city": "Rigolet",
    "lat": 54.166667,
    "lng": -58.433333,
    "country": "Canada",
    "iso2": "CA",
    "admin": "Newfoundland and Labrador",
    "capital": "",
    "population": 124,
    "population_proper": 124
  },
  {
    "city": "Lansdowne House",
    "lat": 52.216667,
    "lng": -87.883333,
    "country": "Canada",
    "iso2": "CA",
    "admin": "Ontario",
    "capital": "",
    "population": 120,
    "population_proper": 120
  },
  {
    "city": "Salluit",
    "lat": 62.2,
    "lng": -75.633333,
    "country": "Canada",
    "iso2": "CA",
    "admin": "Québec",
    "capital": "",
    "population": 106,
    "population_proper": 106
  },
  {
    "city": "Łutselk’e",
    "lat": 62.4,
    "lng": -110.733333,
    "country": "Canada",
    "iso2": "CA",
    "admin": "Northwest Territories",
    "capital": "",
    "population": 102,
    "population_proper": 102
  },
  {
    "city": "Uranium City",
    "lat": 59.566667,
    "lng": -108.616667,
    "country": "Canada",
    "iso2": "CA",
    "admin": "Saskatchewan",
    "capital": "",
    "population": 89,
    "population_proper": 89
  },
  {
    "city": "Burwash Landing",
    "lat": 61.35,
    "lng": -139,
    "country": "Canada",
    "iso2": "CA",
    "admin": "Yukon",
    "capital": "",
    "population": 73,
    "population_proper": 73
  },
  {
    "city": "Grise Fiord",
    "lat": 76.416667,
    "lng": -82.95,
    "country": "Canada",
    "iso2": "CA",
    "admin": "Nunavut",
    "capital": "",
    "population": 23,
    "population_proper": 23
  },
  {
    "city": "Big Beaverhouse",
    "lat": 52.95,
    "lng": -89.883333,
    "country": "Canada",
    "iso2": "CA",
    "admin": "Ontario",
    "capital": "",
    "population": 10,
    "population_proper": 10
  },
  {
    "city": "Island Lake",
    "lat": 53.966667,
    "lng": -94.766667,
    "country": "Canada",
    "iso2": "CA",
    "admin": "Manitoba",
    "capital": "",
    "population": 10,
    "population_proper": 10
  },
  {
    "city": "Ennadai",
    "lat": 61.133333,
    "lng": -100.883333,
    "country": "Canada",
    "iso2": "CA",
    "admin": "Nunavut",
    "capital": "",
    "population": 0,
    "population_proper": 0
  }
]